cgback/__init__.py
cgback/backmapper.py
cgback/backmapper_app.py
cgback/clash.py
cgback/dataloader.py
cgback/dataset.py
cgback/diffuser.py
cgback/egnn.py
cgback/hydrogen.py
cgback/minimization.py
cgback/parser.py
cgback/penetration.py
cgback/schedulers.py
cgback/system.py
cgback/checkpoints/protein-carbon-alpha-cutoff-008-steps-010-layers-003-hidden-128.pt
cgback/checkpoints/protein-carbon-alpha-cutoff-008-steps-020-layers-002-hidden-128.pt
cgback/checkpoints/protein-carbon-alpha-cutoff-008-steps-020-layers-003-hidden-128.pt
cgback/checkpoints/protein-carbon-alpha-cutoff-008-steps-020-layers-004-hidden-128.pt
cgback-1.0.3.dist-info/METADATA
cgback-1.0.3.dist-info/WHEEL
cgback-1.0.3.dist-info/entry_points.txt
cgback-1.0.3.dist-info/licenses/LICENSE
cgback-1.0.3.dist-info/RECORD
