Metadata-Version: 2.4
Name: cgback
Version: 1.0.3
Summary: Deep learning tool for backmapping coarse-grained to all-atom
Project-URL: Repository, https://github.com/bondrewd/cgback
Author-email: Diego Ugarte <diego.ugarte@outlook.com>
License: MIT License
License-File: LICENSE
Classifier: Operating System :: OS Independent
Classifier: Programming Language :: Python :: 3
Requires-Python: >=3.10.0
Requires-Dist: numpy>=2.1.0
Requires-Dist: rich>=13.9.4
Requires-Dist: scipy>=1.15.0
Requires-Dist: torch>=2.5.0
Provides-Extra: openmm
Requires-Dist: openmm>=8.2.0; extra == 'openmm'
Provides-Extra: openmm-cuda12
Requires-Dist: openmm[cuda12]>=8.2.0; extra == 'openmm-cuda12'
